{
  "source": "https://www.kantar.com/north-america/solutions/brand-growth",
  "qa": [
    {
      "questions": [
        "How does Kantar approach brand growth?",
        "What levers drive Meaningful Different Salient brands?"
      ],
      "answer": "Kantar’s solutions tie growth to building brands that are meaningful, different, and salient, enabled by creative, media, innovation, and experience optimization connected to commercial outcomes.",
      "implication": [
        "Measure MDS and link to activation and pricing power in planning.",
        "Optimize creative and media for reach and distinctive assets.",
        "Use innovation and experience metrics to sustain long‑term growth."
      ]
    }
  ]
}
